[
  {"tz": "328", "name": "Aachen",                       "taufdatum": "03.07.2003", "bemerkung": ""},
  {"tz": "309", "name": "Aalen",                        "taufdatum": "21.06.2008", "bemerkung": "HotSpot"},
  {"tz": "1503", "name": "Altenbeken",                  "taufdatum": "11.07.2003", "bemerkung": ""},
  {"tz": "4651", "name": "Amsterdam",                   "taufdatum": "06.10.2003", "bemerkung": "Nederlandse Spoorwegen (NS), Stadtname zu Beginn in blau geschrieben, aktuell in rot"},
  {"tz": "5507", "name": "Arhus",                       "taufdatum": "12.09.2008", "bemerkung": "DSB Zulassung"},
  {"tz": "4652", "name": "Arnhem",                      "taufdatum": "20.03.2003", "bemerkung": "Nederlandse Spoorwegen (NS), Stadtname zu Beginn klein an der Spitze des Zuges, danach groß in blau, aktuell in rot"},
  {"tz": "1125", "name": "Arnstadt",                    "taufdatum": "01.05.2004", "bemerkung": ""},
  {"tz": "109",  "name": "Aschaffenburg",               "taufdatum": "21.04.2004", "bemerkung": ""},
  {"tz": "332",  "name": "Augsburg",                    "taufdatum": "21.11.2002", "bemerkung": "HotSpot"},
  {"tz": "241",  "name": "Bad Hersfeld",                "taufdatum": "06.12.2003", "bemerkung": ""},
  {"tz": "1165", "name": "Bad Oeynhausen",              "taufdatum": "17.05.2006", "bemerkung": ""},
  {"tz": "159",  "name": "Bad Oldesloe",                "taufdatum": "03.03.2004", "bemerkung": "Zugtaufe fand in Hamburg Hbf statt"},
  {"tz": "305",  "name": "Baden-Baden",                 "taufdatum": "05.11.2006", "bemerkung": "HotSpot"},
  {"tz": "1172", "name": "Bamberg",                     "taufdatum": "10.05.2003", "bemerkung": "ex Tz 1114; 12/2006: Tz 1114 wechselt in den DB/ÖBB Fahrzeug-Pool, darauf wechselte der Stadtname an Tz 1172"},
  {"tz": "177",  "name": "Basel",                       "taufdatum": "18.06.2004", "bemerkung": "SBB Zulassung; Zugtaufe fand im Rahmen einer Messeveranstaltung in Düsseldorf statt"},
  {"tz": "243",  "name": "Bautzen/Budyšin",             "taufdatum": "02.06.2004", "bemerkung": "Zugtaufe fand in Dresden-Neustadt statt"},
  {"tz": "161",  "name": "Bebra",                       "taufdatum": "19.07.2003", "bemerkung": "HotSpot"},
  {"tz": "217",  "name": "Bergen auf Rügen",            "taufdatum": "09.07.2005", "bemerkung": ""},
  {"tz": "314",  "name": "Bergisch Gladbach",           "taufdatum": "02.11.2006", "bemerkung": "Zugtaufe fand in Köln Hbf statt"},
  {"tz": "1108", "name": "Berlin",                      "taufdatum": "31.10.2002", "bemerkung": "ex Tz 1111; 12/2004: Namenstausch mit Tz 1108 \"Hansestadt Wismar\""},
  {"tz": "204",  "name": "Bielefeld",                   "taufdatum": "15.11.2002", "bemerkung": ""},
  {"tz": "215",  "name": "Bitterfeld",                  "taufdatum": "17.07.2004", "bemerkung": ""},
  {"tz": "240",  "name": "Bochum",                      "taufdatum": "09.07.2003", "bemerkung": ""},
  {"tz": "208",  "name": "Bonn",                        "taufdatum": "17.12.2002", "bemerkung": ""},
  {"tz": "231",  "name": "Brandenburg an der Havel",    "taufdatum": "11.05.2004", "bemerkung": ""},
  {"tz": "218",  "name": "Braunschweig",                "taufdatum": "12.11.2002", "bemerkung": ""},
  {"tz": "176",  "name": "Bremen",                      "taufdatum": "12.12.2002", "bemerkung": "SBB Zulassung"},
  {"tz": "178",  "name": "Bremerhaven",                 "taufdatum": "13.11.2003", "bemerkung": "SBB Zulassung; HotSpot"},
  {"tz": "184",  "name": "Bruchsal",                    "taufdatum": "23.07.2003", "bemerkung": "SBB Zulassung; Verkehrte in verkürzter Länge von 06/1993–02/1994 in den USA bei Amtrak"},
  {"tz": "180",  "name": "Castrop-Rauxel",              "taufdatum": "04.11.2004", "bemerkung": "SBB Zulassung; HotSpot"},
  {"tz": "361",  "name": "Celle",                       "taufdatum": "29.11.2008", "bemerkung": ""},
  {"tz": "1176", "name": "Coburg",                      "taufdatum": "06.10.2003", "bemerkung": "ex Tz 1115; 12/2006: Tz 1115 wechselt in den DB/ÖBB Fahrzeug-Pool, darauf wechselte der Stadtname an Tz 1176"},
  {"tz": "203",  "name": "Cottbus/Chóśebuz",            "taufdatum": "07.12.2003", "bemerkung": ""},
  {"tz": "168",  "name": "Crailsheim",                  "taufdatum": "19.10.2004", "bemerkung": "ÖBB Zulassung"},
  {"tz": "1180", "name": "Darmstadt",                   "taufdatum": "30.11.2002", "bemerkung": "ex ICE T5/Tz 1580; SBB Zulassung; 2007: Tz 1580 erhielt zwei Mittelwagen von Tz 1120 \"Gotha\""},
  {"tz": "230",  "name": "Delitzsch",                   "taufdatum": "09.10.2004", "bemerkung": ""},
  {"tz": "216",  "name": "Dessau",                      "taufdatum": "12.12.2002", "bemerkung": ""},
  {"tz": "303",  "name": "Dortmund",                    "taufdatum": "28.11.2002", "bemerkung": "HotSpot"},
  {"tz": "1105", "name": "Dresden",                     "taufdatum": "20.12.2002", "bemerkung": ""},
  {"tz": "319",  "name": "Duisburg",                    "taufdatum": "08.10.2003", "bemerkung": "HotSpot"},
  {"tz": "4611", "name": "Düsseldorf",                  "taufdatum": "09.12.2002", "bemerkung": "NS Zulassung"},
  {"tz": "222",  "name": "Eberswalde",                  "taufdatum": "12.05.2007", "bemerkung": ""},
  {"tz": "1501", "name": "Eisenach",                    "taufdatum": "13.05.2003", "bemerkung": ""},
  {"tz": "1104", "name": "Erfurt",                      "taufdatum": "21.11.2002", "bemerkung": ""},
  {"tz": "1117", "name": "Erlangen",                    "taufdatum": "30.06.2004", "bemerkung": ""},
  {"tz": "239",  "name": "Essen",                       "taufdatum": "20.11.2002", "bemerkung": ""},
  {"tz": "333",  "name": "Esslingen am Neckar",         "taufdatum": "06.2009",    "bemerkung": ""},
  {"tz": "154",  "name": "Flensburg",                   "taufdatum": "25.08.2003", "bemerkung": "ex Tz 102; Tz 154 ehemals \"Heppenheim/Bergstraße\" (nach Redesign abgegeben an Tz 156)"},
  {"tz": "210",  "name": "Fontanestadt Neuruppin",      "taufdatum": "18.03.2006", "bemerkung": "Zugtaufe fand in Berlin-Spandau statt"},
  {"tz": "4685", "name": "Forbach/Lorraine",            "taufdatum": "16.09.2006", "bemerkung": "ex Tz 4612; SNCF Zulassung; ehemals Stadtname \"Montabaur\" (abgegeben an Tz 312); 2006/2007: Umbau zum Tz 4685"},
  {"tz": "113",  "name": "Frankenthal/Pfalz",           "taufdatum": "19.05.2005", "bemerkung": ""},
  {"tz": "232",  "name": "Frankfurt (Oder)",            "taufdatum": "21.06.2003", "bemerkung": ""},
  {"tz": "4610", "name": "Frankfurt am Main",           "taufdatum": "04.11.2002", "bemerkung": "NS Zulassung"},
  {"tz": "301",  "name": "Freiburg im Breisgau",        "taufdatum": "29.01.2006", "bemerkung": "HotSpot"},
  {"tz": "156",  "name": "Freilassing",                 "taufdatum": "04.09.2004", "bemerkung": ""},
  {"tz": "114",  "name": "Friedrichshafen",             "taufdatum": "14.06.2005", "bemerkung": "HotSpot; Zugtaufe fand in Ulm Hbf statt"},
  {"tz": "187",  "name": "Fulda",                       "taufdatum": "27.11.2002", "bemerkung": "SBB Zulassung"},
  {"tz": "324",  "name": "Fürth",                       "taufdatum": "15.09.2007", "bemerkung": "HotSpot"},
  {"tz": "167",  "name": "Garmisch-Partenkirchen",      "taufdatum": "18.02.2006", "bemerkung": "ÖBB Zulassung; ehemals Stadtname \"Rüdesheim am Rhein\" (abgegeben an Tz 188)"},
  {"tz": "162",  "name": "Geisenheim/Rheingau",         "taufdatum": "10.11.2005", "bemerkung": "ÖBB Zulassung; Zugtaufe fand in Wiesbaden Hbf statt"},
  {"tz": "166",  "name": "Gelnhausen",                  "taufdatum": "24.04.2009", "bemerkung": "ÖBB Zulassung; Zugtaufe fand in Hanau Hbf statt"},
  {"tz": "110",  "name": "Gelsenkirchen",               "taufdatum": "07.09.2004", "bemerkung": ""},
  {"tz": "101",  "name": "Gießen",                      "taufdatum": "13.07.2004", "bemerkung": "ehemals Ideenzug; Tz 101 trug kurzzeitig den Stadtnamen \"Ludwigshafen am Rhein\""},
  {"tz": "1520", "name": "Gotha",                       "taufdatum": "28.04.2003", "bemerkung": "ex ICE T7/Tz 1120; 2007: Tz 1120 gab zwei Mittelwagen an Tz 1580 \"Darmstadt\" ab"},
  {"tz": "235",  "name": "Görlitz",                     "taufdatum": "03.12.2003", "bemerkung": "Zugtaufe fand in Dresden-Neustadt statt"},
  {"tz": "330",  "name": "Göttingen",                   "taufdatum": "22.01.2003", "bemerkung": "HotSpot"},
  {"tz": "1523", "name": "Hansestadt Greifswald",       "taufdatum": "26.09.2003", "bemerkung": "ex ICE T7/Tz 1123; 2007: Tz 1123 gab zwei Mittelwagen an Tz 1583 \"Oberursel (Taunus)\" ab"},
  {"tz": "1109", "name": "Güstrow",                     "taufdatum": "21.06.2003", "bemerkung": ""},
  {"tz": "158",  "name": "Gütersloh",                   "taufdatum": "14.07.2004", "bemerkung": ""},
  {"tz": "219",  "name": "Hagen",                       "taufdatum": "19.07.2003", "bemerkung": ""},
  {"tz": "1173", "name": "Halle (Saale)",               "taufdatum": "06.12.2002", "bemerkung": "ex Tz 1116; 12/2006: Tz 1116 wechselt in den DB/ÖBB Fahrzeug-Pool, darauf wechselte der Stadtname an Tz 1173"},
  {"tz": "1112", "name": "Freie und Hansestadt Hamburg","taufdatum": "06.11.2002", "bemerkung": ""},
  {"tz": "214",  "name": "Hamm (Westf.)",               "taufdatum": "27.09.2003", "bemerkung": ""},
  {"tz": "152",  "name": "Hanau",                       "taufdatum": "05.07.2004", "bemerkung": ""},
  {"tz": "4607", "name": "Hannover",                    "taufdatum": "08.01.2003", "bemerkung": "NS Zulassung"},
  {"tz": "1504", "name": "Heidelberg",                  "taufdatum": "05.12.2002", "bemerkung": ""},
  {"tz": "156",  "name": "Heppenheim/Bergstraße",       "taufdatum": "13.06.2004", "bemerkung": "ex Tz 154; nach Redesign erhielt Tz 154 den Stadtnamen \"Flensburg\""},
  {"tz": "351",  "name": "Herford",                     "taufdatum": "17.05.2006", "bemerkung": ""},
  {"tz": "171",  "name": "Heusenstamm",                 "taufdatum": "20.03.2009", "bemerkung": "SBB Zulassung; Zugtaufe fand in Frankfurt/Main Hbf statt"},
  {"tz": "185",  "name": "Hildesheim",                  "taufdatum": "29.01.2003", "bemerkung": "SBB Zulassung"},
  {"tz": "117",  "name": "Hof",                         "taufdatum": "06.10.2005", "bemerkung": "Zugtaufe fand in Nürnberg Hbf statt"},
  {"tz": "1521", "name": "Homburg/Saar",                "taufdatum": "09.07.2003", "bemerkung": "ex ICE T7/Tz 1121; 2007: Tz 1121 gab zwei Mittelwagen an Tz 1581 \"Horb am Neckar\" ab"},
  {"tz": "1181", "name": "Horb am Neckar",              "taufdatum": "23.06.2003", "bemerkung": "ex ICE T5/Tz 1581; SBB Zulassung; 2007: Tz 1581 erhielt zwei Mittelwagen von Tz 1121 \"Homburg/Saar\""},
  {"tz": "1153", "name": "Ilmenau",                     "taufdatum": "01.09.2007", "bemerkung": ""},
  {"tz": "336",  "name": "Ingolstadt",                  "taufdatum": "27.11.2003", "bemerkung": ""},
  {"tz": "181",  "name": "Interlaken",                  "taufdatum": "07.12.2007", "bemerkung": "SBB Zulassung; HotSpot"},
  {"tz": "106",  "name": "Itzehoe",                     "taufdatum": "28.06.2005", "bemerkung": "ex Tz 107; 2006: ehemals Stadtname \"Plattling\"; Namenstausch nach Redesign"},
  {"tz": "1130", "name": "Jena",                        "taufdatum": "27.11.2002", "bemerkung": ""},
  {"tz": "5518", "name": "Jever",                       "taufdatum": "18.10.2008", "bemerkung": "DSB Zulassung"},
  {"tz": "236",  "name": "Jüterbog",                    "taufdatum": "28.04.2007", "bemerkung": ""},
  {"tz": "1184", "name": "Kaiserslautern",              "taufdatum": "26.03.2003", "bemerkung": "ex ICE T5/Tz 1584; SBB Zulassung; 2006: Tz 1584 erhielt zwei Mittelwagen von Tz 1124 \"Hansestadt Rostock\""},
  {"tz": "1502", "name": "Karlsruhe",                   "taufdatum": "18.12.2002", "bemerkung": ""},
  {"tz": "1506", "name": "Kassel",                      "taufdatum": "17.12.2002", "bemerkung": ""},
  {"tz": "1129", "name": "Kiel",                        "taufdatum": "20.11.2002", "bemerkung": ""},
  {"tz": "5517", "name": "København",                   "taufdatum": "07.12.2007", "bemerkung": "DSB Zulassung"},
  {"tz": "244",  "name": "Koblenz",                     "taufdatum": "29.03.2003", "bemerkung": ""},
  {"tz": "4682", "name": "Köln",                        "taufdatum": "10.12.2002", "bemerkung": "ex Tz 4609; SNCF Zulassung; 2006/2007: Umbau zum Tz 4682"},
  {"tz": "335",  "name": "Konstanz",                    "taufdatum": "19.04.2008", "bemerkung": "HotSpot"},
  {"tz": "321",  "name": "Krefeld",                     "taufdatum": "21.11.2003", "bemerkung": "HotSpot; Zusammenstoß mit einem Traktor am 01.04.2004 in Istein (ICE 600)"},
  {"tz": "172",  "name": "Landshut",                    "taufdatum": "07.07.2007", "bemerkung": "ex Tz 157; SBB Zulassung; Tz 172 trug während Redesign kurzzeitig den Stadtnamen \"Mülheim (Ruhr)\""},
  {"tz": "1126", "name": "Leipzig",                     "taufdatum": "13.12.2002", "bemerkung": ""},
  {"tz": "108",  "name": "Lichtenfels",                 "taufdatum": "27.07.2004", "bemerkung": ""},
  {"tz": "4606", "name": "Limburg an der Lahn",         "taufdatum": "24.01.2004", "bemerkung": "NS Zulassung"},
  {"tz": "1192", "name": "Linz",                        "taufdatum": "22.10.2008", "bemerkung": "ÖBB Zulassung"},
  {"tz": "221",  "name": "Lübbenau/Spreewald",          "taufdatum": "27.03.2004", "bemerkung": ""},
  {"tz": "302",  "name": "Hansestadt Lübeck",           "taufdatum": "10.02.2004", "bemerkung": "ex ICE TD/Tz 5517; HotSpot; 02/2004: erhielt den Stadtnamen vom ICE TD Tz 5517"},
  {"tz": "190",  "name": "Ludwigshafen am Rhein",       "taufdatum": "10.02.2004", "bemerkung": "ex Tz 101; SBB Zulassung; Tz 101 trug nach Redesign kurzzeitig den Stadtnamen"},
  {"tz": "227",  "name": "Ludwigslust",                 "taufdatum": "21.08.2004", "bemerkung": ""},
  {"tz": "120",  "name": "Lüneburg",                    "taufdatum": "13.08.2003", "bemerkung": ""},
  {"tz": "226",  "name": "Lutherstadt Wittenberg",      "taufdatum": "26.11.2002", "bemerkung": ""},
  {"tz": "206",  "name": "Magdeburg",                   "taufdatum": "25.11.2002", "bemerkung": ""},
  {"tz": "1182", "name": "Mainz",                       "taufdatum": "17.01.2003", "bemerkung": "ex ICE T5/Tz 1582; SBB Zulassung; 2007: Tz 1582 erhielt zwei Mittelwagen von Tz 1122 \"Torgau\""},
  {"tz": "4603", "name": "Mannheim",                    "taufdatum": "24.02.2003", "bemerkung": "NS Zulassung"},
  {"tz": "1505", "name": "Marburg",                     "taufdatum": "05.06.2003", "bemerkung": ""},
  {"tz": "1160", "name": "Markt Holzkirchen",           "taufdatum": "26.05.2007", "bemerkung": ""},
  {"tz": "220",  "name": "Meiningen",                   "taufdatum": "01.10.2005", "bemerkung": "Zugtaufe fand in Eisenach statt"},
  {"tz": "1119", "name": "Meißen",                      "taufdatum": "09.11.2003", "bemerkung": ""},
  {"tz": "112",  "name": "Memmingen",                   "taufdatum": "15.07.2003", "bemerkung": "ex ICE TD/Tz 5505; 02/2004: erhielt den Stadtnamen vom ICE TD Tz 5505"},
  {"tz": "234",  "name": "Minden (Westf.)",             "taufdatum": "22.06.2003", "bemerkung": ""},
  {"tz": "312",  "name": "Montabaur",                   "taufdatum": "09.12.2002", "bemerkung": "ex Tz 4612; HotSpot; 2006: erhielt den Stadtnamen vom Tz 4612"},
  {"tz": "104",  "name": "Mühldorf a. Inn",             "taufdatum": "20.09.2003", "bemerkung": "ex ICE TD/Tz 5511; 02/2004: erhielt den Stadtnamen vom ICE TD Tz 5511"},
  {"tz": "160",  "name": "Mülheim an der Ruhr",         "taufdatum": "30.09.2004", "bemerkung": "HotSpot; zum Taufzeitpunkt war der Stadtname fehlerhaft angeschrieben: \"Mühlheim (Ruhr)\"; nach Redesign \"Mülheim an der Ruhr\""},
  {"tz": "304",  "name": "München",                     "taufdatum": "10.01.2003", "bemerkung": "HotSpot"},
  {"tz": "318",  "name": "Münster (Westf.)",            "taufdatum": "10.07.2003", "bemerkung": ""},
  {"tz": "213",  "name": "Nauen",                       "taufdatum": "01.12.2007", "bemerkung": ""},
  {"tz": "1110", "name": "Naumburg (Saale)",            "taufdatum": "22.11.2003", "bemerkung": ""},
  {"tz": "1102", "name": "Neubrandenburg",              "taufdatum": "30.09.2003", "bemerkung": ""},
  {"tz": "153",  "name": "Neumünster",                  "taufdatum": "20.08.2003", "bemerkung": "Unfall am 16.04.2006 in Riedstadt-Wolfskehlen (ICE 990)"},
  {"tz": "326",  "name": "Neunkirchen",                 "taufdatum": "10.11.2007", "bemerkung": "HotSpot"},
  {"tz": "1101", "name": "Neustadt an der Weinstraße",  "taufdatum": "26.06.2003", "bemerkung": ""},
  {"tz": "237",  "name": "Neustrelitz",                 "taufdatum": "30.10.2008", "bemerkung": ""},
  {"tz": "111",  "name": "Nürnberg",                    "taufdatum": "19.11.2002", "bemerkung": "ex ICE TD/Tz 5504; 1. Redesign ICE; Unfall am 26.04.2008 im Landrückentunnel bei Fulda (ICE 885); 02/2004: erhielt den Stadtnamen vom ICE TD Tz 5504"},
  {"tz": "307",  "name": "Oberhausen",                  "taufdatum": "02.09.2004", "bemerkung": "HotSpot"},
  {"tz": "1183", "name": "Oberursel (Taunus)",          "taufdatum": "09.05.2004", "bemerkung": "ex ICE T5/Tz 1583; SBB Zulassung; 2007: Tz 1583 erhielt zwei Mittelwagen von Tz 1123 \"Hansestadt Greifswald\""},
  {"tz": "105",  "name": "Offenbach am Main",           "taufdatum": "26.08.2003", "bemerkung": "HotSpot"},
  {"tz": "334",  "name": "Offenburg",                   "taufdatum": "22.11.2003", "bemerkung": "HotSpot"},
  {"tz": "228",  "name": "Oldenburg (Oldb)",            "taufdatum": "05.08.2003", "bemerkung": ""},
  {"tz": "119",  "name": "Osnabrück",                   "taufdatum": "19.06.2003", "bemerkung": "HotSpot"},
  {"tz": "1171", "name": "Oschatz",                     "taufdatum": "30.03.2006", "bemerkung": ""},
  {"tz": "1103", "name": "Paderborn",                   "taufdatum": "25.06.2003", "bemerkung": ""},
  {"tz": "1159", "name": "Passau",                      "taufdatum": "27.06.2003", "bemerkung": "ex Tz 1106; Teilweise ausgebrannt 06.01.2004 Abstellanlage Leipzig; nach Brand Stadtnamen an Tz 1159 abgegeben – Tz 1106 abgestellt"},
  {"tz": "116",  "name": "Pforzheim",                   "taufdatum": "01.07.2004", "bemerkung": ""},
  {"tz": "1107", "name": "Pirna",                       "taufdatum": "14.06.2003", "bemerkung": ""},
  {"tz": "107",  "name": "Plattling",                   "taufdatum": "09.06.2005", "bemerkung": "ex Tz 106; 2006: ehemals Stadtname \"Itzehoe\"; Namenstausch nach Redesign"},
  {"tz": "1118", "name": "Plauen/Vogtland",             "taufdatum": "11.03.2004", "bemerkung": "Zugtaufe fand in Reichenbach statt"},
  {"tz": "212",  "name": "Potsdam",                     "taufdatum": "19.03.2003", "bemerkung": ""},
  {"tz": "242",  "name": "Quedlinburg",                 "taufdatum": "04.05.2004", "bemerkung": "Zugtaufe fand in Magdeburg Hbf statt"},
  {"tz": "1177", "name": "Rathenow",                    "taufdatum": "15.07.2006", "bemerkung": ""},
  {"tz": "325",  "name": "Ravensburg",                  "taufdatum": "15.04.2004", "bemerkung": "HotSpot; Zugtaufe fand in Ulm Hbf statt"},
  {"tz": "317",  "name": "Recklinghausen",              "taufdatum": "15.07.2003", "bemerkung": ""},
  {"tz": "115",  "name": "Regensburg",                  "taufdatum": "28.01.2003", "bemerkung": "ex ICE TD/Tz 5501; 02/2004: erhielt den Stadtnamen vom ICE TD Tz 5501"},
  {"tz": "1128", "name": "Reutlingen",                  "taufdatum": "30.11.2004", "bemerkung": ""},
  {"tz": "201",  "name": "Rheinsberg",                  "taufdatum": "15.10.2005", "bemerkung": "Zugtaufe fand in Potsdam Hbf statt"},
  {"tz": "209",  "name": "Riesa",                       "taufdatum": "30.08.2003", "bemerkung": ""},
  {"tz": "155",  "name": "Rosenheim",                   "taufdatum": "28.04.2003", "bemerkung": ""},
  {"tz": "1524", "name": "Hansestadt Rostock",          "taufdatum": "20.09.2003", "bemerkung": "ex ICE T7/Tz 1124; 2006: Tz 1124 gab zwei Mittelwagen an Tz 1584 \"Kaiserslautern\" ab"},
  {"tz": "188",  "name": "Rüdesheim am Rhein",          "taufdatum": "24.11.2004", "bemerkung": "ex Tz 167; SBB Zulassung; 03/2006: erhielt den Stadtnamen vom Tz 167 (jetzt Garmisch-Partenkirchen)"},
  {"tz": "224",  "name": "Saalfeld (Saale)",            "taufdatum": "19.06.2004", "bemerkung": ""},
  {"tz": "238",  "name": "Saarbrücken",                 "taufdatum": "07.07.2005", "bemerkung": ""},
  {"tz": "1191", "name": "Salzburg",                    "taufdatum": "09.12.2006", "bemerkung": "ex Tz 1115; 12/2006: ehemals Stadtname \"Coburg\" (jetzt Tz 1176), Tz 1115 wechselt in den DB/ÖBB Fahrzeug-Pool, Umbeschriftung in Tz 1191"},
  {"tz": "323",  "name": "Schaffhausen",                "taufdatum": "10.07.2008", "bemerkung": "HotSpot"},
  {"tz": "4686", "name": "Schwäbisch Hall",             "taufdatum": "16.09.2004", "bemerkung": "ex Tz 4613; SNCF Zulassung; 2006/2007: Umbau zum Tz 4686"},
  {"tz": "223",  "name": "Schwerin",                    "taufdatum": "03.10.2003", "bemerkung": ""},
  {"tz": "316",  "name": "Siegburg",                    "taufdatum": "22.07.2003", "bemerkung": "HotSpot"},
  {"tz": "315",  "name": "Singen (Hohenwiel)",          "taufdatum": "07.06.2008", "bemerkung": "HotSpot"},
  {"tz": "322",  "name": "Solingen",                    "taufdatum": "02.07.2003", "bemerkung": "HotSpot"},
  {"tz": "1154", "name": "Sonneberg",                   "taufdatum": "27.09.2008", "bemerkung": ""},
  {"tz": "358",  "name": "St. Ingbert",                 "taufdatum": "10.05.2008", "bemerkung": ""},
  {"tz": "207",  "name": "Stendal",                     "taufdatum": "13.01.2003", "bemerkung": ""},
  {"tz": "1113", "name": "Hansestadt Stralsund",        "taufdatum": "24.05.2003", "bemerkung": ""},
  {"tz": "337",  "name": "Stuttgart",                   "taufdatum": "19.11.2002", "bemerkung": ""},
  {"tz": "229",  "name": "Templin",                     "taufdatum": "25.03.2006", "bemerkung": "Zugtaufe fand in Berlin-Spandau statt"},
  {"tz": "183",  "name": "Timmendorfer Strand",         "taufdatum": "04.02.2002", "bemerkung": "ex Tz 173; SBB Zulassung; Zugtaufe fand in Hamburg Hbf statt; Tz 173 Unfall am 28.04.2006 in Thun (CH) (ICE 278); 05/2007: erhielt den Stadtnamen vom Tz 173"},
  {"tz": "1522", "name": "Torgau",                      "taufdatum": "12.05.2004", "bemerkung": "ex ICE T7/Tz 1122; 2007: Tz 1122 gab zwei Mittelwagen an Tz 1582 \"Mainz\" ab"},
  {"tz": "1152", "name": "Travemünde",                  "taufdatum": "13.12.2008", "bemerkung": "Zugtaufe fand in Lübeck statt"},
  {"tz": "313",  "name": "Treuchtlingen",               "taufdatum": "22.09.2004", "bemerkung": ""},
  {"tz": "1131", "name": "Trier",                       "taufdatum": "11.05.2004", "bemerkung": ""},
  {"tz": "211",  "name": "Uelzen",                      "taufdatum": "30.08.2008", "bemerkung": ""},
  {"tz": "233",  "name": "Ulm",                         "taufdatum": "18.11.2002", "bemerkung": ""},
  {"tz": "1156", "name": "Waren (Müritz)",              "taufdatum": "20.05.2006", "bemerkung": ""},
  {"tz": "1178", "name": "Ostseebad Warnemünde",        "taufdatum": "12.06.2007", "bemerkung": ""},
  {"tz": "5510", "name": "Wehrheim (Taunus)",           "taufdatum": "27.10.2007", "bemerkung": "DSB Zulassung"},
  {"tz": "1127", "name": "Weimar",                      "taufdatum": "17.01.2003", "bemerkung": ""},
  {"tz": "331",  "name": "Westerland/Sylt",             "taufdatum": "29.01.2003", "bemerkung": "ex ICE TD/Tz 5520; 02/2004: erhielt den Stadtnamen vom ICE TD Tz 5520"},
  {"tz": "1190", "name": "Wien",                        "taufdatum": "08.12.2007", "bemerkung": "ÖBB Zulassung"},
  {"tz": "311",  "name": "Wiesbaden",                   "taufdatum": "15.12.2002", "bemerkung": "HotSpot"},
  {"tz": "1111", "name": "Hansestadt Wismar",           "taufdatum": "02.08.2003", "bemerkung": "ex Tz 1108; 12/2004: Namenstausch mit Tz 1111 \"Berlin\""},
  {"tz": "1132", "name": "Wittenberge",                 "taufdatum": "24.08.2004", "bemerkung": ""},
  {"tz": "310",  "name": "Wolfsburg",                   "taufdatum": "23.01.2003", "bemerkung": "Entgleisung am 09.07.2008 im Kölner Hbf (ICE 518)"},
  {"tz": "169",  "name": "Worms",                       "taufdatum": "12.09.2006", "bemerkung": "HotSpot"},
  {"tz": "202",  "name": "Wuppertal",                   "taufdatum": "01.07.2003", "bemerkung": ""},
  {"tz": "4680", "name": "Würzburg",                    "taufdatum": "20.11.2002", "bemerkung": "ex Tz 4605; SNCF Zulassung; 2006: Umbau zum Tz 4680"},
  {"tz": "174",  "name": "Zürich",                      "taufdatum": "20.01.2006", "bemerkung": "ex Tz 181; SBB Zulassung; HotSpot; 05–09/2007: erhielt kurzzeitig den Stadtnamen nach Redesign vom Tz 174"},
  {"tz": "205",  "name": "Zwickau",                     "taufdatum": "31.07.2004", "bemerkung": ""}
]
